aws_account/__init__.py
aws_account/cli.py
aws_account/test/test_cli.py
aws_account-0.2.0.dist-info/entry_points.txt
aws_account-0.2.0.dist-info/LICENSE
aws_account-0.2.0.dist-info/WHEEL
aws_account-0.2.0.dist-info/METADATA
aws_account-0.2.0.dist-info/RECORD
